{
  "net.minecraft.client.telemetry.events.AggregatedTelemetryEvent": {
    "className": "AggregatedTelemetryEvent",
    "fullName": "net.minecraft.client.telemetry.events.AggregatedTelemetryEvent",
    "packageName": "net.minecraft.client.telemetry.events",
    "filePath": "/net\\minecraft\\client\\telemetry\\events\\AggregatedTelemetryEvent.java",
    "classType": "class",
    "modifiers": [
      "public",
      "abstract"
    ],
    "superClass": "",
    "interfaces": [],
    "imports": [
      "java.time.Duration",
      "java.time.Instant",
      "javax.annotation.Nullable",
      "net.minecraft.client.telemetry.TelemetryEventSender",
      "net.minecraftforge.api.distmarker.Dist",
      "net.minecraftforge.api.distmarker.OnlyIn"
    ],
    "classComment": "",
    "methods": [
      {
        "name": "start",
        "returnType": "void",
        "parameters": [],
        "modifiers": [
          "public"
        ],
        "comment": "",
        "javadocTags": [],
        "exceptions": [],
        "lineRange": {
          "start": 19,
          "end": 23
        },
        "isConstructor": false
      },
      {
        "name": "tick",
        "returnType": "void",
        "parameters": [
          {
            "name": "pSender",
            "type": "TelemetryEventSender",
            "isVarArgs": false,
            "isFinal": false
          }
        ],
        "modifiers": [
          "public"
        ],
        "comment": "",
        "javadocTags": [],
        "exceptions": [],
        "lineRange": {
          "start": 25,
          "end": 37
        },
        "isConstructor": false
      },
      {
        "name": "shouldTakeSample",
        "returnType": "boolean",
        "parameters": [],
        "modifiers": [
          "public"
        ],
        "comment": "",
        "javadocTags": [],
        "exceptions": [],
        "lineRange": {
          "start": 39,
          "end": 41
        },
        "isConstructor": false
      },
      {
        "name": "shouldSentEvent",
        "returnType": "boolean",
        "parameters": [],
        "modifiers": [
          "public"
        ],
        "comment": "",
        "javadocTags": [],
        "exceptions": [],
        "lineRange": {
          "start": 43,
          "end": 45
        },
        "isConstructor": false
      },
      {
        "name": "stop",
        "returnType": "void",
        "parameters": [],
        "modifiers": [
          "public"
        ],
        "comment": "",
        "javadocTags": [],
        "exceptions": [],
        "lineRange": {
          "start": 47,
          "end": 49
        },
        "isConstructor": false
      },
      {
        "name": "getSampleCount",
        "returnType": "int",
        "parameters": [],
        "modifiers": [
          "protected"
        ],
        "comment": "",
        "javadocTags": [],
        "exceptions": [],
        "lineRange": {
          "start": 51,
          "end": 53
        },
        "isConstructor": false
      },
      {
        "name": "takeSample",
        "returnType": "void",
        "parameters": [],
        "modifiers": [
          "public",
          "abstract"
        ],
        "comment": "",
        "javadocTags": [],
        "exceptions": [],
        "lineRange": {
          "start": 55,
          "end": 55
        },
        "isConstructor": false
      },
      {
        "name": "sendEvent",
        "returnType": "void",
        "parameters": [
          {
            "name": "pSender",
            "type": "TelemetryEventSender",
            "isVarArgs": false,
            "isFinal": false
          }
        ],
        "modifiers": [
          "public",
          "abstract"
        ],
        "comment": "",
        "javadocTags": [],
        "exceptions": [],
        "lineRange": {
          "start": 57,
          "end": 57
        },
        "isConstructor": false
      }
    ],
    "fields": [
      {
        "name": "SAMPLE_INTERVAL_MS",
        "type": "int",
        "modifiers": [
          "private",
          "static",
          "final"
        ],
        "comment": "",
        "initialValue": "60000",
        "lineRange": {
          "start": 12,
          "end": 12
        }
      },
      {
        "name": "SAMPLES_PER_EVENT",
        "type": "int",
        "modifiers": [
          "private",
          "static",
          "final"
        ],
        "comment": "",
        "initialValue": "10",
        "lineRange": {
          "start": 13,
          "end": 13
        }
      },
      {
        "name": "sampleCount",
        "type": "int",
        "modifiers": [
          "private"
        ],
        "comment": "",
        "initialValue": "",
        "lineRange": {
          "start": 14,
          "end": 14
        }
      },
      {
        "name": "ticking",
        "type": "boolean",
        "modifiers": [
          "private"
        ],
        "comment": "",
        "initialValue": "false",
        "lineRange": {
          "start": 15,
          "end": 15
        }
      },
      {
        "name": "lastSampleTime",
        "type": "Instant",
        "modifiers": [
          "private"
        ],
        "comment": "",
        "initialValue": "",
        "lineRange": {
          "start": 17,
          "end": 17
        }
      }
    ],
    "innerClasses": [],
    "lineRange": {
      "start": 11,
      "end": 58
    },
    "sourceFilePath": "/java-sources/net/minecraft/client/telemetry/events/AggregatedTelemetryEvent.java"
  },
  "net.minecraft.client.telemetry.events.GameLoadTimesEvent": {
    "className": "GameLoadTimesEvent",
    "fullName": "net.minecraft.client.telemetry.events.GameLoadTimesEvent",
    "packageName": "net.minecraft.client.telemetry.events",
    "filePath": "/net\\minecraft\\client\\telemetry\\events\\GameLoadTimesEvent.java",
    "classType": "class",
    "modifiers": [
      "public"
    ],
    "superClass": "",
    "interfaces": [],
    "imports": [
      "com.google.common.base.Stopwatch",
      "com.google.common.base.Ticker",
      "com.mojang.logging.LogUtils",
      "com.mojang.serialization.Codec",
      "java.util.HashMap",
      "java.util.Map",
      "java.util.OptionalLong",
      "java.util.concurrent.TimeUnit",
      "java.util.function.Function",
      "net.minecraft.client.telemetry.TelemetryEventSender",
      "net.minecraft.client.telemetry.TelemetryEventType",
      "net.minecraft.client.telemetry.TelemetryProperty",
      "net.minecraftforge.api.distmarker.Dist",
      "net.minecraftforge.api.distmarker.OnlyIn",
      "org.slf4j.Logger"
    ],
    "classComment": "",
    "methods": [
      {
        "name": "GameLoadTimesEvent",
        "returnType": "",
        "parameters": [
          {
            "name": "pTimeSource",
            "type": "Ticker",
            "isVarArgs": false,
            "isFinal": false
          }
        ],
        "modifiers": [
          "protected"
        ],
        "comment": "",
        "javadocTags": [],
        "exceptions": [],
        "lineRange": {
          "start": 27,
          "end": 29
        },
        "isConstructor": true
      },
      {
        "name": "beginStep",
        "returnType": "void",
        "parameters": [
          {
            "name": "pMeasurement",
            "type": "TelemetryProperty<GameLoadTimesEvent.Measurement>",
            "isVarArgs": false,
            "isFinal": false
          }
        ],
        "modifiers": [
          "public",
          "synchronized"
        ],
        "comment": "",
        "javadocTags": [],
        "exceptions": [],
        "lineRange": {
          "start": 31,
          "end": 35
        },
        "isConstructor": false
      },
      {
        "name": "beginStep",
        "returnType": "void",
        "parameters": [
          {
            "name": "pMeasurement",
            "type": "TelemetryProperty<GameLoadTimesEvent.Measurement>",
            "isVarArgs": false,
            "isFinal": false
          },
          {
            "name": "pStopwatch",
            "type": "Stopwatch",
            "isVarArgs": false,
            "isFinal": false
          }
        ],
        "modifiers": [
          "public",
          "synchronized"
        ],
        "comment": "",
        "javadocTags": [],
        "exceptions": [],
        "lineRange": {
          "start": 37,
          "end": 41
        },
        "isConstructor": false
      },
      {
        "name": "beginStep",
        "returnType": "void",
        "parameters": [
          {
            "name": "pMeasurement",
            "type": "TelemetryProperty<GameLoadTimesEvent.Measurement>",
            "isVarArgs": false,
            "isFinal": false
          },
          {
            "name": "param",
            "type": "Object",
            "isVarArgs": false,
            "isFinal": false
          },
          {
            "name": "pStopwatchGetter",
            "type": "Stopwatch>",
            "isVarArgs": false,
            "isFinal": false
          }
        ],
        "modifiers": [
          "private",
          "synchronized"
        ],
        "comment": "",
        "javadocTags": [],
        "exceptions": [],
        "lineRange": {
          "start": 43,
          "end": 45
        },
        "isConstructor": false
      },
      {
        "name": "endStep",
        "returnType": "void",
        "parameters": [
          {
            "name": "pMeasurement",
            "type": "TelemetryProperty<GameLoadTimesEvent.Measurement>",
            "isVarArgs": false,
            "isFinal": false
          }
        ],
        "modifiers": [
          "public",
          "synchronized"
        ],
        "comment": "",
        "javadocTags": [],
        "exceptions": [],
        "lineRange": {
          "start": 47,
          "end": 57
        },
        "isConstructor": false
      },
      {
        "name": "send",
        "returnType": "void",
        "parameters": [
          {
            "name": "pSender",
            "type": "TelemetryEventSender",
            "isVarArgs": false,
            "isFinal": false
          }
        ],
        "modifiers": [
          "public"
        ],
        "comment": "",
        "javadocTags": [],
        "exceptions": [],
        "lineRange": {
          "start": 59,
          "end": 77
        },
        "isConstructor": false
      },
      {
        "name": "setBootstrapTime",
        "returnType": "void",
        "parameters": [
          {
            "name": "pBootstrapTime",
            "type": "long",
            "isVarArgs": false,
            "isFinal": false
          }
        ],
        "modifiers": [
          "public",
          "synchronized"
        ],
        "comment": "",
        "javadocTags": [],
        "exceptions": [],
        "lineRange": {
          "start": 79,
          "end": 81
        },
        "isConstructor": false
      },
      {
        "name": "Measurement",
        "returnType": "record",
        "parameters": [
          {
            "name": "millis",
            "type": "int",
            "isVarArgs": false,
            "isFinal": false
          }
        ],
        "modifiers": [
          "public",
          "static"
        ],
        "comment": "",
        "javadocTags": [],
        "exceptions": [],
        "lineRange": {
          "start": 84,
          "end": 88
        },
        "isConstructor": false
      }
    ],
    "fields": [
      {
        "name": "timeSource",
        "type": "Ticker",
        "modifiers": [
          "private",
          "final"
        ],
        "comment": "",
        "initialValue": "",
        "lineRange": {
          "start": 23,
          "end": 23
        }
      }
    ],
    "innerClasses": [],
    "lineRange": {
      "start": 20,
      "end": 89
    },
    "sourceFilePath": "/java-sources/net/minecraft/client/telemetry/events/GameLoadTimesEvent.java"
  },
  "net.minecraft.client.telemetry.events.PerformanceMetricsEvent": {
    "className": "PerformanceMetricsEvent",
    "fullName": "net.minecraft.client.telemetry.events.PerformanceMetricsEvent",
    "packageName": "net.minecraft.client.telemetry.events",
    "filePath": "/net\\minecraft\\client\\telemetry\\events\\PerformanceMetricsEvent.java",
    "classType": "class",
    "modifiers": [
      "public",
      "final"
    ],
    "superClass": "AggregatedTelemetryEvent",
    "interfaces": [],
    "imports": [
      "it.unimi.dsi.fastutil.longs.LongArrayList",
      "it.unimi.dsi.fastutil.longs.LongList",
      "net.minecraft.client.Minecraft",
      "net.minecraft.client.telemetry.TelemetryEventSender",
      "net.minecraft.client.telemetry.TelemetryEventType",
      "net.minecraft.client.telemetry.TelemetryProperty",
      "net.minecraftforge.api.distmarker.Dist",
      "net.minecraftforge.api.distmarker.OnlyIn"
    ],
    "classComment": "",
    "methods": [
      {
        "name": "tick",
        "returnType": "void",
        "parameters": [
          {
            "name": "pSender",
            "type": "TelemetryEventSender",
            "isVarArgs": false,
            "isFinal": false
          }
        ],
        "modifiers": [
          "public"
        ],
        "comment": "",
        "javadocTags": [],
        "exceptions": [],
        "lineRange": {
          "start": 19,
          "end": 24
        },
        "isConstructor": false
      },
      {
        "name": "resetValues",
        "returnType": "void",
        "parameters": [],
        "modifiers": [
          "private"
        ],
        "comment": "",
        "javadocTags": [],
        "exceptions": [],
        "lineRange": {
          "start": 26,
          "end": 30
        },
        "isConstructor": false
      },
      {
        "name": "takeSample",
        "returnType": "void",
        "parameters": [],
        "modifiers": [
          "public"
        ],
        "comment": "",
        "javadocTags": [],
        "exceptions": [],
        "lineRange": {
          "start": 32,
          "end": 36
        },
        "isConstructor": false
      },
      {
        "name": "takeUsedMemorySample",
        "returnType": "void",
        "parameters": [],
        "modifiers": [
          "private"
        ],
        "comment": "",
        "javadocTags": [],
        "exceptions": [],
        "lineRange": {
          "start": 38,
          "end": 43
        },
        "isConstructor": false
      },
      {
        "name": "sendEvent",
        "returnType": "void",
        "parameters": [
          {
            "name": "pSender",
            "type": "TelemetryEventSender",
            "isVarArgs": false,
            "isFinal": false
          }
        ],
        "modifiers": [
          "public"
        ],
        "comment": "",
        "javadocTags": [],
        "exceptions": [],
        "lineRange": {
          "start": 45,
          "end": 55
        },
        "isConstructor": false
      },
      {
        "name": "toKilobytes",
        "returnType": "long",
        "parameters": [
          {
            "name": "pBytes",
            "type": "long",
            "isVarArgs": false,
            "isFinal": false
          }
        ],
        "modifiers": [
          "private",
          "static"
        ],
        "comment": "",
        "javadocTags": [],
        "exceptions": [],
        "lineRange": {
          "start": 57,
          "end": 59
        },
        "isConstructor": false
      }
    ],
    "fields": [],
    "innerClasses": [],
    "lineRange": {
      "start": 13,
      "end": 60
    },
    "sourceFilePath": "/java-sources/net/minecraft/client/telemetry/events/PerformanceMetricsEvent.java"
  },
  "net.minecraft.client.telemetry.events.WorldLoadEvent": {
    "className": "WorldLoadEvent",
    "fullName": "net.minecraft.client.telemetry.events.WorldLoadEvent",
    "packageName": "net.minecraft.client.telemetry.events",
    "filePath": "/net\\minecraft\\client\\telemetry\\events\\WorldLoadEvent.java",
    "classType": "class",
    "modifiers": [
      "public"
    ],
    "superClass": "",
    "interfaces": [],
    "imports": [
      "javax.annotation.Nullable",
      "net.minecraft.client.Minecraft",
      "net.minecraft.client.telemetry.TelemetryEventSender",
      "net.minecraft.client.telemetry.TelemetryEventType",
      "net.minecraft.client.telemetry.TelemetryProperty",
      "net.minecraft.client.telemetry.TelemetryPropertyMap",
      "net.minecraft.world.level.GameType",
      "net.minecraftforge.api.distmarker.Dist",
      "net.minecraftforge.api.distmarker.OnlyIn"
    ],
    "classComment": "",
    "methods": [
      {
        "name": "WorldLoadEvent",
        "returnType": "",
        "parameters": [
          {
            "name": "pMinigameName",
            "type": "String",
            "isVarArgs": false,
            "isFinal": false
          }
        ],
        "modifiers": [
          "public"
        ],
        "comment": "",
        "javadocTags": [],
        "exceptions": [],
        "lineRange": {
          "start": 23,
          "end": 25
        },
        "isConstructor": true
      },
      {
        "name": "addProperties",
        "returnType": "void",
        "parameters": [
          {
            "name": "pBuilder",
            "type": "TelemetryPropertyMap.Builder",
            "isVarArgs": false,
            "isFinal": false
          }
        ],
        "modifiers": [
          "public"
        ],
        "comment": "",
        "javadocTags": [],
        "exceptions": [],
        "lineRange": {
          "start": 27,
          "end": 33
        },
        "isConstructor": false
      },
      {
        "name": "send",
        "returnType": "boolean",
        "parameters": [
          {
            "name": "pSender",
            "type": "TelemetryEventSender",
            "isVarArgs": false,
            "isFinal": false
          }
        ],
        "modifiers": [
          "public"
        ],
        "comment": "",
        "javadocTags": [],
        "exceptions": [],
        "lineRange": {
          "start": 43,
          "end": 57
        },
        "isConstructor": false
      },
      {
        "name": "setGameMode",
        "returnType": "void",
        "parameters": [
          {
            "name": "pGameMode",
            "type": "GameType",
            "isVarArgs": false,
            "isFinal": false
          },
          {
            "name": "pIsHardcore",
            "type": "boolean",
            "isVarArgs": false,
            "isFinal": false
          }
        ],
        "modifiers": [
          "public"
        ],
        "comment": "",
        "javadocTags": [],
        "exceptions": [],
        "lineRange": {
          "start": 59,
          "end": 79
        },
        "isConstructor": false
      },
      {
        "name": "setServerBrand",
        "returnType": "void",
        "parameters": [
          {
            "name": "pServerBrand",
            "type": "String",
            "isVarArgs": false,
            "isFinal": false
          }
        ],
        "modifiers": [
          "public"
        ],
        "comment": "",
        "javadocTags": [],
        "exceptions": [],
        "lineRange": {
          "start": 81,
          "end": 83
        },
        "isConstructor": false
      }
    ],
    "fields": [
      {
        "name": "eventSent",
        "type": "boolean",
        "modifiers": [
          "private"
        ],
        "comment": "",
        "initialValue": "",
        "lineRange": {
          "start": 15,
          "end": 15
        }
      },
      {
        "name": "gameMode",
        "type": "TelemetryProperty.GameMode",
        "modifiers": [
          "private"
        ],
        "comment": "",
        "initialValue": "",
        "lineRange": {
          "start": 17,
          "end": 17
        }
      },
      {
        "name": "serverBrand",
        "type": "String",
        "modifiers": [
          "private"
        ],
        "comment": "",
        "initialValue": "",
        "lineRange": {
          "start": 19,
          "end": 19
        }
      },
      {
        "name": "minigameName",
        "type": "String",
        "modifiers": [
          "private",
          "final"
        ],
        "comment": "",
        "initialValue": "",
        "lineRange": {
          "start": 21,
          "end": 21
        }
      }
    ],
    "innerClasses": [],
    "lineRange": {
      "start": 14,
      "end": 84
    },
    "sourceFilePath": "/java-sources/net/minecraft/client/telemetry/events/WorldLoadEvent.java"
  },
  "net.minecraft.client.telemetry.events.WorldLoadTimesEvent": {
    "className": "WorldLoadTimesEvent",
    "fullName": "net.minecraft.client.telemetry.events.WorldLoadTimesEvent",
    "packageName": "net.minecraft.client.telemetry.events",
    "filePath": "/net\\minecraft\\client\\telemetry\\events\\WorldLoadTimesEvent.java",
    "classType": "class",
    "modifiers": [
      "public"
    ],
    "superClass": "",
    "interfaces": [],
    "imports": [
      "java.time.Duration",
      "javax.annotation.Nullable",
      "net.minecraft.client.telemetry.TelemetryEventSender",
      "net.minecraft.client.telemetry.TelemetryEventType",
      "net.minecraft.client.telemetry.TelemetryProperty",
      "net.minecraftforge.api.distmarker.Dist",
      "net.minecraftforge.api.distmarker.OnlyIn"
    ],
    "classComment": "",
    "methods": [
      {
        "name": "WorldLoadTimesEvent",
        "returnType": "",
        "parameters": [
          {
            "name": "pNewWorld",
            "type": "boolean",
            "isVarArgs": false,
            "isFinal": false
          },
          {
            "name": "pWordLoadDuration",
            "type": "Duration",
            "isVarArgs": false,
            "isFinal": false
          }
        ],
        "modifiers": [
          "public"
        ],
        "comment": "",
        "javadocTags": [],
        "exceptions": [],
        "lineRange": {
          "start": 17,
          "end": 20
        },
        "isConstructor": true
      },
      {
        "name": "send",
        "returnType": "void",
        "parameters": [
          {
            "name": "pSender",
            "type": "TelemetryEventSender",
            "isVarArgs": false,
            "isFinal": false
          }
        ],
        "modifiers": [
          "public"
        ],
        "comment": "",
        "javadocTags": [],
        "exceptions": [],
        "lineRange": {
          "start": 22,
          "end": 30
        },
        "isConstructor": false
      }
    ],
    "fields": [
      {
        "name": "newWorld",
        "type": "boolean",
        "modifiers": [
          "private",
          "final"
        ],
        "comment": "",
        "initialValue": "",
        "lineRange": {
          "start": 13,
          "end": 13
        }
      },
      {
        "name": "worldLoadDuration",
        "type": "Duration",
        "modifiers": [
          "private",
          "final"
        ],
        "comment": "",
        "initialValue": "",
        "lineRange": {
          "start": 15,
          "end": 15
        }
      }
    ],
    "innerClasses": [],
    "lineRange": {
      "start": 12,
      "end": 31
    },
    "sourceFilePath": "/java-sources/net/minecraft/client/telemetry/events/WorldLoadTimesEvent.java"
  },
  "net.minecraft.client.telemetry.events.WorldUnloadEvent": {
    "className": "WorldUnloadEvent",
    "fullName": "net.minecraft.client.telemetry.events.WorldUnloadEvent",
    "packageName": "net.minecraft.client.telemetry.events",
    "filePath": "/net\\minecraft\\client\\telemetry\\events\\WorldUnloadEvent.java",
    "classType": "class",
    "modifiers": [
      "public"
    ],
    "superClass": "",
    "interfaces": [],
    "imports": [
      "java.time.Duration",
      "java.time.Instant",
      "java.util.Optional",
      "net.minecraft.client.telemetry.TelemetryEventSender",
      "net.minecraft.client.telemetry.TelemetryEventType",
      "net.minecraft.client.telemetry.TelemetryProperty",
      "net.minecraftforge.api.distmarker.Dist",
      "net.minecraftforge.api.distmarker.OnlyIn"
    ],
    "classComment": "",
    "methods": [
      {
        "name": "onPlayerInfoReceived",
        "returnType": "void",
        "parameters": [],
        "modifiers": [
          "public"
        ],
        "comment": "",
        "javadocTags": [],
        "exceptions": [],
        "lineRange": {
          "start": 19,
          "end": 25
        },
        "isConstructor": false
      },
      {
        "name": "setTime",
        "returnType": "void",
        "parameters": [
          {
            "name": "pTime",
            "type": "long",
            "isVarArgs": false,
            "isFinal": false
          }
        ],
        "modifiers": [
          "public"
        ],
        "comment": "",
        "javadocTags": [],
        "exceptions": [],
        "lineRange": {
          "start": 27,
          "end": 33
        },
        "isConstructor": false
      },
      {
        "name": "getTimeInSecondsSinceLoad",
        "returnType": "int",
        "parameters": [
          {
            "name": "pWordLoadedTime",
            "type": "Instant",
            "isVarArgs": false,
            "isFinal": false
          }
        ],
        "modifiers": [
          "private"
        ],
        "comment": "",
        "javadocTags": [],
        "exceptions": [],
        "lineRange": {
          "start": 35,
          "end": 38
        },
        "isConstructor": false
      },
      {
        "name": "send",
        "returnType": "void",
        "parameters": [
          {
            "name": "pSender",
            "type": "TelemetryEventSender",
            "isVarArgs": false,
            "isFinal": false
          }
        ],
        "modifiers": [
          "public"
        ],
        "comment": "",
        "javadocTags": [],
        "exceptions": [],
        "lineRange": {
          "start": 40,
          "end": 47
        },
        "isConstructor": false
      }
    ],
    "fields": [
      {
        "name": "NOT_TRACKING_TIME",
        "type": "int",
        "modifiers": [
          "private",
          "static",
          "final"
        ],
        "comment": "",
        "initialValue": "-1",
        "lineRange": {
          "start": 14,
          "end": 14
        }
      },
      {
        "name": "totalTicks",
        "type": "long",
        "modifiers": [
          "private"
        ],
        "comment": "",
        "initialValue": "",
        "lineRange": {
          "start": 16,
          "end": 16
        }
      },
      {
        "name": "lastGameTime",
        "type": "long",
        "modifiers": [
          "private"
        ],
        "comment": "",
        "initialValue": "",
        "lineRange": {
          "start": 17,
          "end": 17
        }
      }
    ],
    "innerClasses": [],
    "lineRange": {
      "start": 13,
      "end": 48
    },
    "sourceFilePath": "/java-sources/net/minecraft/client/telemetry/events/WorldUnloadEvent.java"
  }
}